.hgignore
.hgtags
ABOUT.txt
CHANGES.txt
COPYRIGHT.txt
LICENSE-OSM.txt
LICENSE.txt
README.txt
base.cfg
index.txt
setup.py
doc/about.txt
doc/conf.py
doc/modules.txt
doc/tests.txt
tl/__init__.py
tl.geodrawing.egg-info/PKG-INFO
tl.geodrawing.egg-info/SOURCES.txt
tl.geodrawing.egg-info/dependency_links.txt
tl.geodrawing.egg-info/entry_points.txt
tl.geodrawing.egg-info/namespace_packages.txt
tl.geodrawing.egg-info/not-zip-safe
tl.geodrawing.egg-info/requires.txt
tl.geodrawing.egg-info/top_level.txt
tl/geodrawing/__init__.py
tl/geodrawing/controller.py
tl/geodrawing/controller.txt
tl/geodrawing/demo.py
tl/geodrawing/gtkwidget.py
tl/geodrawing/osm.py
tl/geodrawing/tests.py
tl/geodrawing/tile.py
tl/geodrawing/testimages/default.png
tl/geodrawing/testimages/transform_for_geo.png
tl/geodrawing/testimages/transformed_for_geo-2.png
tl/geodrawing/testimages/transformed_for_geo.png
tl/geodrawing/testimages/wide.png
tl/geodrawing/testimages/zoom-2.png
tl/geodrawing/testtiles/osm/0-0-0.png
tl/geodrawing/testtiles/osm/2-2-2.png