Metadata-Version: 1.0
Name: tl.geodrawing
Version: 0.1
Summary: A geographic pygtk drawing area.
